icd10/__init__.py
icd10/__version__.py
icd10/icd10.json.gz
icd10_cm-0.0.3.dist-info/LICENSE
icd10_cm-0.0.3.dist-info/METADATA
icd10_cm-0.0.3.dist-info/WHEEL
icd10_cm-0.0.3.dist-info/top_level.txt
icd10_cm-0.0.3.dist-info/RECORD
