Metadata-Version: 2.1
Name: icd10-cm
Version: 0.0.3
Summary: ICD-10 codes for diseases, signs and symptoms, abnormal findings, complaints, social circumstances, and external causes of injury or disease
Home-page: https://github.com/bryand1/icd10-cm
Author: Bryan Andrade
Author-email: me@bryanandrade.com
License: MIT
Platform: UNKNOWN
Classifier: Development Status :: 3 - Alpha
Classifier: License :: OSI Approved :: MIT License
Classifier: Intended Audience :: Developers
Classifier: Natural Language :: English
Classifier: Programming Language :: Python
Classifier: Programming Language :: Python :: 3
Classifier: Programming Language :: Python :: 3.6
Classifier: Programming Language :: Python :: 3.7
Classifier: Programming Language :: Python :: Implementation :: CPython
Requires-Python: >=3.6.0
